image_regist/__init__.py
image_regist/tools.py
image_regist-0.0.5.dist-info/METADATA
image_regist-0.0.5.dist-info/WHEEL
image_regist-0.0.5.dist-info/top_level.txt
image_regist-0.0.5.dist-info/RECORD
