Metadata-Version: 2.1
Name: image-regist
Version: 0.0.5
Summary: Image Registration Library
Home-page: UNKNOWN
Author: Muhamad Fikri Sunandar
License: UNKNOWN
Platform: UNKNOWN
Classifier: Programming Language :: Python :: 3
Classifier: License :: OSI Approved :: MIT License
Classifier: Operating System :: OS Independent
Requires-Python: >=3.6
Requires-Dist: numpy (==1.21.6)
Requires-Dist: Pillow (==9.3.0)
Requires-Dist: scipy (==1.7.3)
